anycubic_cloud_api/__init__.py
anycubic_cloud_api/anycubic_api.py
anycubic_cloud_api/api/__init__.py
anycubic_cloud_api/api/base.py
anycubic_cloud_api/api/functions.py
anycubic_cloud_api/api/mqtt.py
anycubic_cloud_api/const/__init__.py
anycubic_cloud_api/const/api_endpoints.py
anycubic_cloud_api/const/const.py
anycubic_cloud_api/const/enums.py
anycubic_cloud_api/const/mqtt.py
anycubic_cloud_api/data_models/__init__.py
anycubic_cloud_api/data_models/consumable.py
anycubic_cloud_api/data_models/files.py
anycubic_cloud_api/data_models/gcode_file.py
anycubic_cloud_api/data_models/orders.py
anycubic_cloud_api/data_models/print_response.py
anycubic_cloud_api/data_models/print_speed_mode.py
anycubic_cloud_api/data_models/printer.py
anycubic_cloud_api/data_models/printer_properties.py
anycubic_cloud_api/data_models/printing_settings.py
anycubic_cloud_api/data_models/project.py
anycubic_cloud_api/exceptions/__init__.py
anycubic_cloud_api/exceptions/error_strings.py
anycubic_cloud_api/exceptions/exceptions.py
anycubic_cloud_api/helpers/__init__.py
anycubic_cloud_api/helpers/helpers.py
anycubic_cloud_api/models/__init__.py
anycubic_cloud_api/models/auth.py
anycubic_cloud_api/models/cloud_upload.py
anycubic_cloud_api/models/http.py
anycubic_cloud_api/resources/__init__.py
anycubic_cloud_api/resources/anycubic_mqqt_tls_ca.crt
anycubic_cloud_api/resources/anycubic_mqqt_tls_client.crt
anycubic_cloud_api/resources/anycubic_mqqt_tls_client.key
anycubic_cloud_mcp-0.2.6.dist-info/licenses/LICENSE
anycubic_mcp/__init__.py
anycubic_mcp/client.py
anycubic_mcp/config.py
anycubic_mcp/extractor.py
anycubic_mcp/install.py
anycubic_mcp/mcp_server.py
anycubic_cloud_mcp-0.2.6.dist-info/METADATA
anycubic_cloud_mcp-0.2.6.dist-info/WHEEL
anycubic_cloud_mcp-0.2.6.dist-info/entry_points.txt
anycubic_cloud_mcp-0.2.6.dist-info/top_level.txt
anycubic_cloud_mcp-0.2.6.dist-info/RECORD
