Metadata-Version: 2.4
Name: anycubic-cloud-mcp
Version: 0.2.6
Summary: MCP server and CLI for Anycubic Cloud printers.
Author: Anycubic MCP Contributors
License-Expression: GPL-3.0-or-later
Requires-Python: >=3.11
License-File: LICENSE
Requires-Dist: aiofiles>=24.1.0
Requires-Dist: aiohttp>=3.9.5
Requires-Dist: anyio>=4.4.0
Requires-Dist: bcrypt>=4.1.3
Requires-Dist: cryptography>=42.0.5
Requires-Dist: mcp
Requires-Dist: paho-mqtt>=2.1.0
Requires-Dist: sse-starlette>=2.1.0
Requires-Dist: starlette>=0.37.2
Requires-Dist: uvicorn>=0.30.0
Dynamic: license-file
